{
  "26400": {
    "投保金額等級": "1",
    "月投保金額": "26400",
    "本人": "409",
    "本人+1": "818",
    "本人+2": "1227",
    "本人+3": "1636",
    "單位": "1286",
    "政府": "214"
  },
  "27600": {
    "投保金額等級": "2",
    "月投保金額": "27600",
    "本人": "428",
    "本人+1": "856",
    "本人+2": "1284",
    "本人+3": "1712",
    "單位": "1344",
    "政府": "224"
  },
  "28800": {
    "投保金額等級": "3",
    "月投保金額": "28800",
    "本人": "447",
    "本人+1": "894",
    "本人+2": "1341",
    "本人+3": "1788",
    "單位": "1403",
    "政府": "234"
  },
  "30300": {
    "投保金額等級": "4",
    "月投保金額": "30300",
    "本人": "470",
    "本人+1": "940",
    "本人+2": "1410",
    "本人+3": "1880",
    "單位": "1476",
    "政府": "246"
  },
  "31800": {
    "投保金額等級": "5",
    "月投保金額": "31800",
    "本人": "493",
    "本人+1": "986",
    "本人+2": "1479",
    "本人+3": "1972",
    "單位": "1549",
    "政府": "258"
  },
  "33300": {
    "投保金額等級": "6",
    "月投保金額": "33300",
    "本人": "516",
    "本人+1": "1032",
    "本人+2": "1548",
    "本人+3": "2064",
    "單位": "1622",
    "政府": "270"
  },
  "34800": {
    "投保金額等級": "7",
    "月投保金額": "34800",
    "本人": "540",
    "本人+1": "1080",
    "本人+2": "1620",
    "本人+3": "2160",
    "單位": "1695",
    "政府": "282"
  },
  "36300": {
    "投保金額等級": "8",
    "月投保金額": "36300",
    "本人": "563",
    "本人+1": "1126",
    "本人+2": "1689",
    "本人+3": "2252",
    "單位": "1768",
    "政府": "295"
  },
  "38200": {
    "投保金額等級": "9",
    "月投保金額": "38200",
    "本人": "592",
    "本人+1": "1184",
    "本人+2": "1776",
    "本人+3": "2368",
    "單位": "1860",
    "政府": "310"
  },
  "40100": {
    "投保金額等級": "10",
    "月投保金額": "40100",
    "本人": "622",
    "本人+1": "1244",
    "本人+2": "1866",
    "本人+3": "2488",
    "單位": "1953",
    "政府": "325"
  },
  "42000": {
    "投保金額等級": "11",
    "月投保金額": "42000",
    "本人": "651",
    "本人+1": "1302",
    "本人+2": "1953",
    "本人+3": "2604",
    "單位": "2045",
    "政府": "341"
  },
  "43900": {
    "投保金額等級": "12",
    "月投保金額": "43900",
    "本人": "681",
    "本人+1": "1362",
    "本人+2": "2043",
    "本人+3": "2724",
    "單位": "2138",
    "政府": "356"
  },
  "45800": {
    "投保金額等級": "13",
    "月投保金額": "45800",
    "本人": "710",
    "本人+1": "1420",
    "本人+2": "2130",
    "本人+3": "2840",
    "單位": "2231",
    "政府": "372"
  },
  "48200": {
    "投保金額等級": "14",
    "月投保金額": "48200",
    "本人": "748",
    "本人+1": "1496",
    "本人+2": "2244",
    "本人+3": "2992",
    "單位": "2347",
    "政府": "391"
  },
  "50600": {
    "投保金額等級": "15",
    "月投保金額": "50600",
    "本人": "785",
    "本人+1": "1570",
    "本人+2": "2355",
    "本人+3": "3140",
    "單位": "2464",
    "政府": "411"
  },
  "53000": {
    "投保金額等級": "16",
    "月投保金額": "53000",
    "本人": "822",
    "本人+1": "1644",
    "本人+2": "2466",
    "本人+3": "3288",
    "單位": "2581",
    "政府": "430"
  },
  "55400": {
    "投保金額等級": "17",
    "月投保金額": "55400",
    "本人": "859",
    "本人+1": "1718",
    "本人+2": "2577",
    "本人+3": "3436",
    "單位": "2698",
    "政府": "450"
  },
  "57800": {
    "投保金額等級": "18",
    "月投保金額": "57800",
    "本人": "896",
    "本人+1": "1792",
    "本人+2": "2688",
    "本人+3": "3584",
    "單位": "2815",
    "政府": "469"
  },
  "60800": {
    "投保金額等級": "19",
    "月投保金額": "60800",
    "本人": "943",
    "本人+1": "1886",
    "本人+2": "2829",
    "本人+3": "3772",
    "單位": "2961",
    "政府": "494"
  },
  "63800": {
    "投保金額等級": "20",
    "月投保金額": "63800",
    "本人": "990",
    "本人+1": "1980",
    "本人+2": "2970",
    "本人+3": "3960",
    "單位": "3107",
    "政府": "518"
  },
  "66800": {
    "投保金額等級": "21",
    "月投保金額": "66800",
    "本人": "1036",
    "本人+1": "2072",
    "本人+2": "3108",
    "本人+3": "4144",
    "單位": "3253",
    "政府": "542"
  },
  "69800": {
    "投保金額等級": "22",
    "月投保金額": "69800",
    "本人": "1083",
    "本人+1": "2166",
    "本人+2": "3249",
    "本人+3": "4332",
    "單位": "3399",
    "政府": "567"
  },
  "72800": {
    "投保金額等級": "23",
    "月投保金額": "72800",
    "本人": "1129",
    "本人+1": "2258",
    "本人+2": "3387",
    "本人+3": "4516",
    "單位": "3545",
    "政府": "591"
  },
  "76500": {
    "投保金額等級": "24",
    "月投保金額": "76500",
    "本人": "1187",
    "本人+1": "2374",
    "本人+2": "3561",
    "本人+3": "4748",
    "單位": "3726",
    "政府": "621"
  },
  "80200": {
    "投保金額等級": "25",
    "月投保金額": "80200",
    "本人": "1244",
    "本人+1": "2488",
    "本人+2": "3732",
    "本人+3": "4976",
    "單位": "3906",
    "政府": "651"
  },
  "83900": {
    "投保金額等級": "26",
    "月投保金額": "83900",
    "本人": "1301",
    "本人+1": "2602",
    "本人+2": "3903",
    "本人+3": "5204",
    "單位": "4086",
    "政府": "681"
  },
  "87600": {
    "投保金額等級": "27",
    "月投保金額": "87600",
    "本人": "1359",
    "本人+1": "2718",
    "本人+2": "4077",
    "本人+3": "5436",
    "單位": "4266",
    "政府": "711"
  },
  "92100": {
    "投保金額等級": "28",
    "月投保金額": "92100",
    "本人": "1428",
    "本人+1": "2856",
    "本人+2": "4284",
    "本人+3": "5712",
    "單位": "4485",
    "政府": "748"
  },
  "96600": {
    "投保金額等級": "29",
    "月投保金額": "96600",
    "本人": "1498",
    "本人+1": "2996",
    "本人+2": "4494",
    "本人+3": "5992",
    "單位": "4705",
    "政府": "784"
  },
  "101100": {
    "投保金額等級": "30",
    "月投保金額": "101100",
    "本人": "1568",
    "本人+1": "3136",
    "本人+2": "4704",
    "本人+3": "6272",
    "單位": "4924",
    "政府": "821"
  },
  "105600": {
    "投保金額等級": "31",
    "月投保金額": "105600",
    "本人": "1638",
    "本人+1": "3276",
    "本人+2": "4914",
    "本人+3": "6552",
    "單位": "5143",
    "政府": "857"
  },
  "110100": {
    "投保金額等級": "32",
    "月投保金額": "110100",
    "本人": "1708",
    "本人+1": "3416",
    "本人+2": "5124",
    "本人+3": "6832",
    "單位": "5362",
    "政府": "894"
  },
  "115500": {
    "投保金額等級": "33",
    "月投保金額": "115500",
    "本人": "1791",
    "本人+1": "3582",
    "本人+2": "5373",
    "本人+3": "7164",
    "單位": "5625",
    "政府": "938"
  },
  "120900": {
    "投保金額等級": "34",
    "月投保金額": "120900",
    "本人": "1875",
    "本人+1": "3750",
    "本人+2": "5625",
    "本人+3": "7500",
    "單位": "5888",
    "政府": "981"
  },
  "126300": {
    "投保金額等級": "35",
    "月投保金額": "126300",
    "本人": "1959",
    "本人+1": "3918",
    "本人+2": "5877",
    "本人+3": "7836",
    "單位": "6151",
    "政府": "1025"
  },
  "131700": {
    "投保金額等級": "36",
    "月投保金額": "131700",
    "本人": "2043",
    "本人+1": "4086",
    "本人+2": "6129",
    "本人+3": "8172",
    "單位": "6414",
    "政府": "1069"
  },
  "137100": {
    "投保金額等級": "37",
    "月投保金額": "137100",
    "本人": "2126",
    "本人+1": "4252",
    "本人+2": "6378",
    "本人+3": "8504",
    "單位": "6677",
    "政府": "1113"
  },
  "142500": {
    "投保金額等級": "38",
    "月投保金額": "142500",
    "本人": "2210",
    "本人+1": "4420",
    "本人+2": "6630",
    "本人+3": "8840",
    "單位": "6940",
    "政府": "1157"
  },
  "147900": {
    "投保金額等級": "39",
    "月投保金額": "147900",
    "本人": "2294",
    "本人+1": "4588",
    "本人+2": "6882",
    "本人+3": "9176",
    "單位": "7203",
    "政府": "1200"
  },
  "150000": {
    "投保金額等級": "40",
    "月投保金額": "150000",
    "本人": "2327",
    "本人+1": "4654",
    "本人+2": "6981",
    "本人+3": "9308",
    "單位": "7305",
    "政府": "1218"
  },
  "156400": {
    "投保金額等級": "41",
    "月投保金額": "156400",
    "本人": "2426",
    "本人+1": "4852",
    "本人+2": "7278",
    "本人+3": "9704",
    "單位": "7617",
    "政府": "1269"
  },
  "162800": {
    "投保金額等級": "42",
    "月投保金額": "162800",
    "本人": "2525",
    "本人+1": "5050",
    "本人+2": "7575",
    "本人+3": "10100",
    "單位": "7929",
    "政府": "1321"
  },
  "169200": {
    "投保金額等級": "43",
    "月投保金額": "169200",
    "本人": "2624",
    "本人+1": "5248",
    "本人+2": "7872",
    "本人+3": "10496",
    "單位": "8240",
    "政府": "1373"
  },
  "175600": {
    "投保金額等級": "44",
    "月投保金額": "175600",
    "本人": "2724",
    "本人+1": "5448",
    "本人+2": "8172",
    "本人+3": "10896",
    "單位": "8552",
    "政府": "1425"
  },
  "182000": {
    "投保金額等級": "45",
    "月投保金額": "182000",
    "本人": "2823",
    "本人+1": "5646",
    "本人+2": "8469",
    "本人+3": "11292",
    "單位": "8864",
    "政府": "1477"
  },
  "189500": {
    "投保金額等級": "46",
    "月投保金額": "189500",
    "本人": "2939",
    "本人+1": "5878",
    "本人+2": "8817",
    "本人+3": "11756",
    "單位": "9229",
    "政府": "1538"
  },
  "197000": {
    "投保金額等級": "47",
    "月投保金額": "197000",
    "本人": "3055",
    "本人+1": "6110",
    "本人+2": "9165",
    "本人+3": "12220",
    "單位": "9594",
    "政府": "1599"
  },
  "204500": {
    "投保金額等級": "48",
    "月投保金額": "204500",
    "本人": "3172",
    "本人+1": "6344",
    "本人+2": "9516",
    "本人+3": "12688",
    "單位": "9959",
    "政府": "1660"
  },
  "212000": {
    "投保金額等級": "49",
    "月投保金額": "212000",
    "本人": "3288",
    "本人+1": "6576",
    "本人+2": "9864",
    "本人+3": "13152",
    "單位": "10325",
    "政府": "1721"
  },
  "219500": {
    "投保金額等級": "50",
    "月投保金額": "219500",
    "本人": "3404",
    "本人+1": "6808",
    "本人+2": "10212",
    "本人+3": "13616",
    "單位": "10690",
    "政府": "1782"
  }
}
